pymsasdax/__init__.py
pymsasdax/dax.py
pymsasdax-2023.1020.dist-info/LICENSE
pymsasdax-2023.1020.dist-info/METADATA
pymsasdax-2023.1020.dist-info/WHEEL
pymsasdax-2023.1020.dist-info/top_level.txt
pymsasdax-2023.1020.dist-info/RECORD
