Metadata-Version: 2.1
Name: pymsasdax
Version: 2023.1020
Summary: Run DAX queries against Analysis Services and get Pandas Dataframes
Author-email: Gage Renzi <gagerenzi+pypy@gmail.com>
License: MIT License
Project-URL: Homepage, https://github.com/grenzi/pymsasdax
Keywords: dax,MSAS,Analysis Services,SSAS,PowerBI,Power BI,XMLA
Classifier: License :: OSI Approved :: MIT License
Classifier: Programming Language :: Python
Classifier: Programming Language :: Python :: 3
Requires-Python: >=3.9
License-File: LICENSE
Requires-Dist: dateparser
Requires-Dist: pandas
Requires-Dist: pythonnet
Provides-Extra: dev
Requires-Dist: black ; extra == 'dev'
Requires-Dist: bumpver ; extra == 'dev'
Requires-Dist: pip-tools ; extra == 'dev'
